{
    "items": [
        {
            "type": "markdown",
            "name": "intro.md"
        },
        {
            "type": "markdown",
            "name": "mg_mqtt_broker_init.md"
        },
        {
            "type": "markdown",
            "name": "mg_mqtt_broker.md"
        },
        {
            "type": "markdown",
            "name": "mg_mqtt_next.md"
        },
        {
            "type": "markdown",
            "name": "struct_mg_mqtt_session.md"
        },
        {
            "type": "markdown",
            "name": "struct_mg_mqtt_broker.md"
        }
    ]
}
